django_gov_notify/__init__.py
django_gov_notify/backends.py
django_gov_notify/message.py
django_gov_notify/utils.py
django_gov_notify-0.6.0.dist-info/LICENCE
django_gov_notify-0.6.0.dist-info/METADATA
django_gov_notify-0.6.0.dist-info/WHEEL
django_gov_notify-0.6.0.dist-info/RECORD
