Metadata-Version: 2.1
Name: django-gov-notify
Version: 0.6.0
Summary: A GOV.UK Notify flavoured Django email backend
Home-page: https://github.com/nimasmi/django-gov-notify
License: BSD-2-Clause
Keywords: email,Django
Author: Nick Smith
Author-email: nick.smith@torchbox.com
Requires-Python: >=3.9,<3.13
Classifier: Development Status :: 4 - Beta
Classifier: Environment :: Web Environment
Classifier: Framework :: Django
Classifier: Framework :: Django :: 4.2
Classifier: Framework :: Django :: 5.0
Classifier: Framework :: Django :: 5.1
Classifier: Intended Audience :: Developers
Classifier: License :: OSI Approved :: BSD License
Classifier: Operating System :: OS Independent
Classifier: Programming Language :: Python :: 3
Classifier: Programming Language :: Python :: 3.9
Classifier: Programming Language :: Python :: 3.10
Classifier: Programming Language :: Python :: 3.11
Classifier: Programming Language :: Python :: 3.12
Classifier: Topic :: Communications :: Email
Requires-Dist: django (>=4.2) ; python_version >= "3.9" and python_version < "3.13"
Requires-Dist: notifications-python-client (>=8.1.0,<9.0.0)
Project-URL: Repository, https://github.com/nimasmi/django-gov-notify
